nmexec_python-1.0.2.dist-info/licenses/LICENSE
pynmexec/__ini__.py
pynmexec/client.py
nmexec_python-1.0.2.dist-info/METADATA
nmexec_python-1.0.2.dist-info/WHEEL
nmexec_python-1.0.2.dist-info/top_level.txt
nmexec_python-1.0.2.dist-info/RECORD
