Metadata-Version: 2.4
Name: nmexec-python
Version: 1.0.2
Summary: Network Model Executor Allows python client support
Requires-Python: >=3.11
License-File: LICENSE
Dynamic: license-file
